[
  {
    "year": 2075,
    "date": "2075/01/01",
    "description": "Confraternização Universal"
  },
  {
    "year": 2075,
    "date": "2075/02/18",
    "description": "Carnaval"
  },
  {
    "year": 2075,
    "date": "2075/02/19",
    "description": "Carnaval"
  },
  {
    "year": 2075,
    "date": "2075/04/05",
    "description": "Paixão de Cristo"
  },
  {
    "year": 2075,
    "date": "2075/04/21",
    "description": "Tiradentes"
  },
  {
    "year": 2075,
    "date": "2075/05/01",
    "description": "Dia do Trabalho"
  },
  {
    "year": 2075,
    "date": "2075/06/06",
    "description": "Corpus Christi"
  },
  {
    "year": 2075,
    "date": "2075/09/07",
    "description": "Independência do Brasil"
  },
  {
    "year": 2075,
    "date": "2075/10/12",
    "description": "Nossa Sr.a Aparecida - Padroeira do Brasil"
  },
  {
    "year": 2075,
    "date": "2075/11/02",
    "description": "Finados"
  },
  {
    "year": 2075,
    "date": "2075/11/15",
    "description": "Proclamação da República"
  },
  {
    "year": 2075,
    "date": "2075/12/25",
    "description": "Natal"
  }
]
